{
  "took": 0,
  "timed_out": false,
  "_shards": {
    "total": 1,
    "successful": 1,
    "skipped": 0,
    "failed": 0
  },
  "hits": {
    "total": {
      "value": 1,
      "relation": "eq"
    },
    "max_score": null,
    "hits": [
      {
        "_index": "geopoints-prod-44836dc4-95be-46f2-9dc2-1f5228eead7d",
        "_id": "Bl0ph5QByzIO-BRUJF3D",
        "_score": null,
        "_source": {
          "incidentId": "A202502080256",
          "polygonCenter": [
            -82.0619100009978,
            27.982439996739124
          ],
          "customerCount": 1,
          "estimatedTimeOfRestoration": "2025-01-21T02:10:00",
          "reason": "Pending Investigation",
          "status": "We're working onsite",
          "updateTime": "2025-01-20T23:40:04"
        },
        "sort": [
          1737416404000,
          "A202502080256"
        ]
      }
    ]
  },
  "cache": true
}
