{
  "took": 0,
  "timed_out": false,
  "_shards": {
    "total": 1,
    "successful": 1,
    "skipped": 0,
    "failed": 0
  },
  "hits": {
    "total": {
      "value": 3,
      "relation": "eq"
    },
    "max_score": null,
    "hits": [
      {
        "_index": "geopoints-prod-ecdcbb2e-8cdc-4497-9794-c04350f42cdf",
        "_id": "TGsiOJUByzIO-BRUIOJq",
        "_score": null,
        "_source": {
          "incidentId": "A202505504495",
          "polygonCenter": [
            -82.10778967838718,
            27.99673536786812
          ],
          "customerCount": 2,
          "estimatedTimeOfRestoration": "2025-02-24T11:10:00",
          "reason": "Pending Investigation",
          "status": "We're on our way to investigate",
          "updateTime": "2025-02-24T08:25:06"
        },
        "sort": [
          1740385506000,
          "A202505504495"
        ]
      },
      {
        "_index": "geopoints-prod-ecdcbb2e-8cdc-4497-9794-c04350f42cdf",
        "_id": "SmsiOJUByzIO-BRUIOJq",
        "_score": null,
        "_source": {
          "incidentId": "A202505505161",
          "polygonCenter": [
            -82.52477035536083,
            28.060767103711804
          ],
          "customerCount": 2,
          "estimatedTimeOfRestoration": "2025-02-24T11:50:00",
          "reason": "Pending Investigation",
          "status": "We're on our way to investigate",
          "updateTime": "2025-02-24T08:25:06"
        },
        "sort": [
          1740385506000,
          "A202505505161"
        ]
      },
      {
        "_index": "geopoints-prod-ecdcbb2e-8cdc-4497-9794-c04350f42cdf",
        "_id": "S2siOJUByzIO-BRUIOJq",
        "_score": null,
        "_source": {
          "incidentId": "A202505505411",
          "polygonCenter": [
            -81.70128000120275,
            28.030329996714705
          ],
          "customerCount": 1,
          "estimatedTimeOfRestoration": "2025-02-24T12:10:00",
          "reason": "Pending Investigation",
          "status": "We're on our way to investigate",
          "updateTime": "2025-02-24T08:25:06"
        },
        "sort": [
          1740385506000,
          "A202505505411"
        ]
      }
    ]
  },
  "cache": true
}
