{
  "took": 1,
  "timed_out": false,
  "_shards": {
    "total": 1,
    "successful": 1,
    "skipped": 0,
    "failed": 0
  },
  "hits": {
    "total": {
      "value": 18,
      "relation": "eq"
    },
    "max_score": null,
    "hits": [
      {
        "_index": "geopoints-prod-bd649c52-0cba-4a92-927f-ab58e2b04ddd",
        "_id": "BlmqP5MByckvcAhRGzVL",
        "_score": null,
        "_source": {
          "incidentId": "A202432301545",
          "polygonCenter": [
            -82.42750724031652,
            28.075580000803768
          ],
          "customerCount": 237,
          "estimatedTimeOfRestoration": "2024-11-18T12:49:00",
          "reason": "Damage to Tampa Electric equipment",
          "status": "We're working onsite",
          "updateTime": "2024-11-18T09:25:12"
        },
        "sort": [
          1731921912000,
          "A202432301545"
        ]
      },
      {
        "_index": "geopoints-prod-bd649c52-0cba-4a92-927f-ab58e2b04ddd",
        "_id": "AlmqP5MByckvcAhRGzVL",
        "_score": null,
        "_source": {
          "incidentId": "A202432306280",
          "polygonCenter": [
            -82.37685700057351,
            28.025548983364615
          ],
          "customerCount": 1,
          "estimatedTimeOfRestoration": "2024-11-18T12:00:00",
          "reason": "Under investigation",
          "status": "We're working onsite",
          "updateTime": "2024-11-18T09:25:12"
        },
        "sort": [
          1731921912000,
          "A202432306280"
        ]
      },
      {
        "_index": "geopoints-prod-bd649c52-0cba-4a92-927f-ab58e2b04ddd",
        "_id": "91mqP5MByckvcAhRGzRL",
        "_score": null,
        "_source": {
          "incidentId": "A202432306883",
          "polygonCenter": [
            -82.22005900865891,
            28.0104000463389
          ],
          "customerCount": 1,
          "estimatedTimeOfRestoration": "2024-11-18T12:50:00",
          "reason": "Pending Investigation",
          "status": "We're aware of the outage",
          "updateTime": "2024-11-18T09:25:12"
        },
        "sort": [
          1731921912000,
          "A202432306883"
        ]
      },
      {
        "_index": "geopoints-prod-bd649c52-0cba-4a92-927f-ab58e2b04ddd",
        "_id": "-FmqP5MByckvcAhRGzRL",
        "_score": null,
        "_source": {
          "incidentId": "A202432307162",
          "polygonCenter": [
            -82.50024000076326,
            27.883049996792906
          ],
          "customerCount": 1,
          "estimatedTimeOfRestoration": "2024-11-18T13:00:00",
          "reason": "Pending Investigation",
          "status": "We're aware of the outage",
          "updateTime": "2024-11-18T09:25:12"
        },
        "sort": [
          1731921912000,
          "A202432307162"
        ]
      },
      {
        "_index": "geopoints-prod-bd649c52-0cba-4a92-927f-ab58e2b04ddd",
        "_id": "A1mqP5MByckvcAhRGzVL",
        "_score": null,
        "_source": {
          "incidentId": "A202432307253",
          "polygonCenter": [
            -82.4940578343776,
            27.99319499671647
          ],
          "customerCount": 7,
          "estimatedTimeOfRestoration": "2024-11-18T13:10:00",
          "reason": "Under investigation",
          "status": "We're working onsite",
          "updateTime": "2024-11-18T09:25:12"
        },
        "sort": [
          1731921912000,
          "A202432307253"
        ]
      },
      {
        "_index": "geopoints-prod-bd649c52-0cba-4a92-927f-ab58e2b04ddd",
        "_id": "_1mqP5MByckvcAhRGzRL",
        "_score": null,
        "_source": {
          "incidentId": "A202432307258",
          "polygonCenter": [
            -82.07403000099092,
            27.985699996737324
          ],
          "customerCount": 1,
          "estimatedTimeOfRestoration": "2024-11-18T13:10:00",
          "reason": "Pending Investigation",
          "status": "We're aware of the outage",
          "updateTime": "2024-11-18T09:25:12"
        },
        "sort": [
          1731921912000,
          "A202432307258"
        ]
      },
      {
        "_index": "geopoints-prod-bd649c52-0cba-4a92-927f-ab58e2b04ddd",
        "_id": "-VmqP5MByckvcAhRGzRL",
        "_score": null,
        "_source": {
          "incidentId": "A202432307281",
          "polygonCenter": [
            -82.44727899440275,
            28.06220009770542
          ],
          "customerCount": 1,
          "estimatedTimeOfRestoration": "2024-11-18T13:10:00",
          "reason": "Pending Investigation",
          "status": "We're aware of the outage",
          "updateTime": "2024-11-18T09:25:12"
        },
        "sort": [
          1731921912000,
          "A202432307281"
        ]
      },
      {
        "_index": "geopoints-prod-bd649c52-0cba-4a92-927f-ab58e2b04ddd",
        "_id": "BFmqP5MByckvcAhRGzVL",
        "_score": null,
        "_source": {
          "incidentId": "A202432307296",
          "polygonCenter": [
            -82.49330661334238,
            27.99319499630957
          ],
          "customerCount": 8,
          "estimatedTimeOfRestoration": "2024-11-18T13:10:00",
          "reason": "Under investigation",
          "status": "We're working onsite",
          "updateTime": "2024-11-18T09:25:12"
        },
        "sort": [
          1731921912000,
          "A202432307296"
        ]
      },
      {
        "_index": "geopoints-prod-bd649c52-0cba-4a92-927f-ab58e2b04ddd",
        "_id": "-lmqP5MByckvcAhRGzRL",
        "_score": null,
        "_source": {
          "incidentId": "A202432307327",
          "polygonCenter": [
            -82.25832000088596,
            27.919529996773637
          ],
          "customerCount": 1,
          "estimatedTimeOfRestoration": "2024-11-18T13:10:00",
          "reason": "Pending Investigation",
          "status": "We're aware of the outage",
          "updateTime": "2024-11-18T09:25:12"
        },
        "sort": [
          1731921912000,
          "A202432307327"
        ]
      },
      {
        "_index": "geopoints-prod-bd649c52-0cba-4a92-927f-ab58e2b04ddd",
        "_id": "-1mqP5MByckvcAhRGzRL",
        "_score": null,
        "_source": {
          "incidentId": "A202432307335",
          "polygonCenter": [
            -82.46939000076723,
            28.048859996698635
          ],
          "customerCount": 1,
          "estimatedTimeOfRestoration": "2024-11-18T13:10:00",
          "reason": "Pending Investigation",
          "status": "We're aware of the outage",
          "updateTime": "2024-11-18T09:25:12"
        },
        "sort": [
          1731921912000,
          "A202432307335"
        ]
      },
      {
        "_index": "geopoints-prod-bd649c52-0cba-4a92-927f-ab58e2b04ddd",
        "_id": "_FmqP5MByckvcAhRGzRL",
        "_score": null,
        "_source": {
          "incidentId": "A202432307342",
          "polygonCenter": [
            -82.60810449178072,
            28.104920065427088
          ],
          "customerCount": 1,
          "estimatedTimeOfRestoration": "2024-11-18T13:10:00",
          "reason": "Pending Investigation",
          "status": "We're aware of the outage",
          "updateTime": "2024-11-18T09:25:12"
        },
        "sort": [
          1731921912000,
          "A202432307342"
        ]
      },
      {
        "_index": "geopoints-prod-bd649c52-0cba-4a92-927f-ab58e2b04ddd",
        "_id": "AFmqP5MByckvcAhRGzVL",
        "_score": null,
        "_source": {
          "incidentId": "A202432307344",
          "polygonCenter": [
            -82.42674000079145,
            28.055479996695322
          ],
          "customerCount": 1,
          "estimatedTimeOfRestoration": "2024-11-18T13:10:00",
          "reason": "Pending Investigation",
          "status": "We're aware of the outage",
          "updateTime": "2024-11-18T09:25:12"
        },
        "sort": [
          1731921912000,
          "A202432307344"
        ]
      },
      {
        "_index": "geopoints-prod-bd649c52-0cba-4a92-927f-ab58e2b04ddd",
        "_id": "AVmqP5MByckvcAhRGzVL",
        "_score": null,
        "_source": {
          "incidentId": "A202432307358",
          "polygonCenter": [
            -82.54736683673292,
            28.07543670087029
          ],
          "customerCount": 8,
          "estimatedTimeOfRestoration": "2024-11-18T13:10:00",
          "reason": "Pending Investigation",
          "status": "We're aware of the outage",
          "updateTime": "2024-11-18T09:25:12"
        },
        "sort": [
          1731921912000,
          "A202432307358"
        ]
      },
      {
        "_index": "geopoints-prod-bd649c52-0cba-4a92-927f-ab58e2b04ddd",
        "_id": "BVmqP5MByckvcAhRGzVL",
        "_score": null,
        "_source": {
          "incidentId": "A202432307406",
          "polygonCenter": [
            -82.47711905018244,
            28.089110910869827
          ],
          "customerCount": 2,
          "estimatedTimeOfRestoration": "2024-11-18T13:20:00",
          "reason": "Under investigation",
          "status": "We're working onsite",
          "updateTime": "2024-11-18T09:25:12"
        },
        "sort": [
          1731921912000,
          "A202432307406"
        ]
      },
      {
        "_index": "geopoints-prod-bd649c52-0cba-4a92-927f-ab58e2b04ddd",
        "_id": "9VmqP5MByckvcAhRGzRL",
        "_score": null,
        "_source": {
          "incidentId": "A202432307443",
          "polygonCenter": [
            -82.57028606594457,
            27.98508051065165
          ],
          "customerCount": 1,
          "estimatedTimeOfRestoration": "2024-11-18T13:20:00",
          "reason": "Pending Investigation",
          "status": "We're aware of the outage",
          "updateTime": "2024-11-18T09:25:12"
        },
        "sort": [
          1731921912000,
          "A202432307443"
        ]
      },
      {
        "_index": "geopoints-prod-bd649c52-0cba-4a92-927f-ab58e2b04ddd",
        "_id": "_VmqP5MByckvcAhRGzRL",
        "_score": null,
        "_source": {
          "incidentId": "A202432307491",
          "polygonCenter": [
            -82.25922450808115,
            27.98750002593552
          ],
          "customerCount": 1,
          "estimatedTimeOfRestoration": "2024-11-18T13:30:00",
          "reason": "Pending Investigation",
          "status": "We're aware of the outage",
          "updateTime": "2024-11-18T09:25:12"
        },
        "sort": [
          1731921912000,
          "A202432307491"
        ]
      },
      {
        "_index": "geopoints-prod-bd649c52-0cba-4a92-927f-ab58e2b04ddd",
        "_id": "9lmqP5MByckvcAhRGzRL",
        "_score": null,
        "_source": {
          "incidentId": "A202432307535",
          "polygonCenter": [
            -82.47575000076297,
            27.954679996752482
          ],
          "customerCount": 1,
          "estimatedTimeOfRestoration": "2024-11-18T13:30:00",
          "reason": "Pending Investigation",
          "status": "We're aware of the outage",
          "updateTime": "2024-11-18T09:25:12"
        },
        "sort": [
          1731921912000,
          "A202432307535"
        ]
      },
      {
        "_index": "geopoints-prod-bd649c52-0cba-4a92-927f-ab58e2b04ddd",
        "_id": "_lmqP5MByckvcAhRGzRL",
        "_score": null,
        "_source": {
          "incidentId": "A202432307538",
          "polygonCenter": [
            -82.54471204213553,
            28.07317940352094
          ],
          "customerCount": 113,
          "estimatedTimeOfRestoration": "2024-11-18T13:30:00",
          "reason": "Pending Investigation",
          "status": "We're aware of the outage",
          "updateTime": "2024-11-18T09:25:12"
        },
        "sort": [
          1731921912000,
          "A202432307538"
        ]
      }
    ]
  },
  "cache": true
}
