{
  "took": 0,
  "timed_out": false,
  "_shards": {
    "total": 1,
    "successful": 1,
    "skipped": 0,
    "failed": 0
  },
  "hits": {
    "total": {
      "value": 5,
      "relation": "eq"
    },
    "max_score": null,
    "hits": [
      {
        "_index": "geopoints-prod-2fe31b91-9152-4354-b73b-0d7e9e01dfd5",
        "_id": "LpNl6pMByzIO-BRUFrcz",
        "_score": null,
        "_source": {
          "incidentId": "A202435608044",
          "polygonCenter": [
            -82.3863200008136,
            27.943419996759246
          ],
          "customerCount": 1,
          "estimatedTimeOfRestoration": "2024-12-21T18:12:00",
          "reason": "Tree or tree limbs in contact with equipment",
          "status": "Additional support enroute",
          "updateTime": "2024-12-21T13:05:04"
        },
        "sort": [
          1734786304000,
          "A202435608044"
        ]
      },
      {
        "_index": "geopoints-prod-2fe31b91-9152-4354-b73b-0d7e9e01dfd5",
        "_id": "L5Nl6pMByzIO-BRUFrcz",
        "_score": null,
        "_source": {
          "incidentId": "A202435611504",
          "polygonCenter": [
            -82.47804000076249,
            28.076199996683137
          ],
          "customerCount": 1,
          "estimatedTimeOfRestoration": "2024-12-21T16:30:00",
          "reason": "Pending Investigation",
          "status": "We're aware of the outage",
          "updateTime": "2024-12-21T13:05:04"
        },
        "sort": [
          1734786304000,
          "A202435611504"
        ]
      },
      {
        "_index": "geopoints-prod-2fe31b91-9152-4354-b73b-0d7e9e01dfd5",
        "_id": "MJNl6pMByzIO-BRUFrcz",
        "_score": null,
        "_source": {
          "incidentId": "A202435611653",
          "polygonCenter": [
            -82.47870000076207,
            28.07552999668333
          ],
          "customerCount": 1,
          "estimatedTimeOfRestoration": "2024-12-21T16:50:00",
          "reason": "Pending Investigation",
          "status": "We're aware of the outage",
          "updateTime": "2024-12-21T13:05:04"
        },
        "sort": [
          1734786304000,
          "A202435611653"
        ]
      },
      {
        "_index": "geopoints-prod-2fe31b91-9152-4354-b73b-0d7e9e01dfd5",
        "_id": "MZNl6pMByzIO-BRUFrcz",
        "_score": null,
        "_source": {
          "incidentId": "A202435611670",
          "polygonCenter": [
            -82.48036000076115,
            28.076219996683133
          ],
          "customerCount": 1,
          "estimatedTimeOfRestoration": "2024-12-21T16:50:00",
          "reason": "Pending Investigation",
          "status": "We're aware of the outage",
          "updateTime": "2024-12-21T13:05:04"
        },
        "sort": [
          1734786304000,
          "A202435611670"
        ]
      },
      {
        "_index": "geopoints-prod-2fe31b91-9152-4354-b73b-0d7e9e01dfd5",
        "_id": "MpNl6pMByzIO-BRUFrcz",
        "_score": null,
        "_source": {
          "incidentId": "A202435611899",
          "polygonCenter": [
            -82.47738132176585,
            28.076026265485762
          ],
          "customerCount": 4,
          "estimatedTimeOfRestoration": "2024-12-21T17:00:00",
          "reason": "Pending Investigation",
          "status": "We're aware of the outage",
          "updateTime": "2024-12-21T13:05:04"
        },
        "sort": [
          1734786304000,
          "A202435611899"
        ]
      }
    ]
  },
  "cache": true
}
