{
  "took": 1,
  "timed_out": false,
  "_shards": {
    "total": 1,
    "successful": 1,
    "skipped": 0,
    "failed": 0
  },
  "hits": {
    "total": {
      "value": 7,
      "relation": "eq"
    },
    "max_score": null,
    "hits": [
      {
        "_index": "geopoints-prod-55ad5d95-0f1d-495e-907c-5dd45a9baf09",
        "_id": "6VNmLpQByzIO-BRUDADA",
        "_score": null,
        "_source": {
          "incidentId": "A202500315242",
          "polygonCenter": [
            -82.25664069585372,
            27.958785189122864
          ],
          "customerCount": 70,
          "estimatedTimeOfRestoration": "2025-01-03T18:30:00",
          "reason": "Pending Investigation",
          "status": "We're on our way to investigate",
          "updateTime": "2025-01-03T18:00:10"
        },
        "sort": [
          1735927210000,
          "A202500315242"
        ]
      },
      {
        "_index": "geopoints-prod-55ad5d95-0f1d-495e-907c-5dd45a9baf09",
        "_id": "6lNmLpQByzIO-BRUDADA",
        "_score": null,
        "_source": {
          "incidentId": "A202500315407",
          "polygonCenter": [
            -82.40077450911548,
            27.981250041873338
          ],
          "customerCount": 1,
          "estimatedTimeOfRestoration": "2025-01-03T18:40:00",
          "reason": "Damage to Tampa Electric equipment",
          "status": "Additional support enroute",
          "updateTime": "2025-01-03T18:00:10"
        },
        "sort": [
          1735927210000,
          "A202500315407"
        ]
      },
      {
        "_index": "geopoints-prod-55ad5d95-0f1d-495e-907c-5dd45a9baf09",
        "_id": "61NmLpQByzIO-BRUDADA",
        "_score": null,
        "_source": {
          "incidentId": "A202500317953",
          "polygonCenter": [
            -82.59979000070827,
            28.11622999665959
          ],
          "customerCount": 1,
          "estimatedTimeOfRestoration": "2025-01-03T20:50:00",
          "reason": "Pending Investigation",
          "status": "We're on our way to investigate",
          "updateTime": "2025-01-03T18:00:10"
        },
        "sort": [
          1735927210000,
          "A202500317953"
        ]
      },
      {
        "_index": "geopoints-prod-55ad5d95-0f1d-495e-907c-5dd45a9baf09",
        "_id": "71NmLpQByzIO-BRUDADA",
        "_score": null,
        "_source": {
          "incidentId": "A202500318183",
          "polygonCenter": [
            -82.5959600007105,
            28.12639999665398
          ],
          "customerCount": 1,
          "estimatedTimeOfRestoration": "2025-01-03T21:10:00",
          "reason": "Pending Investigation",
          "status": "We're on our way to investigate",
          "updateTime": "2025-01-03T18:00:10"
        },
        "sort": [
          1735927210000,
          "A202500318183"
        ]
      },
      {
        "_index": "geopoints-prod-55ad5d95-0f1d-495e-907c-5dd45a9baf09",
        "_id": "7VNmLpQByzIO-BRUDADA",
        "_score": null,
        "_source": {
          "incidentId": "A202500318258",
          "polygonCenter": [
            -82.40015005166347,
            28.02527374926032
          ],
          "customerCount": 1,
          "estimatedTimeOfRestoration": "2025-01-03T21:10:00",
          "reason": "Pending Investigation",
          "status": "We're working onsite",
          "updateTime": "2025-01-03T18:00:10"
        },
        "sort": [
          1735927210000,
          "A202500318258"
        ]
      },
      {
        "_index": "geopoints-prod-55ad5d95-0f1d-495e-907c-5dd45a9baf09",
        "_id": "7FNmLpQByzIO-BRUDADA",
        "_score": null,
        "_source": {
          "incidentId": "A202500318680",
          "polygonCenter": [
            -82.44611022656724,
            27.681643536634382
          ],
          "customerCount": 26,
          "estimatedTimeOfRestoration": "2025-01-03T21:40:00",
          "reason": "Pending Investigation",
          "status": "We're on our way to investigate",
          "updateTime": "2025-01-03T18:00:10"
        },
        "sort": [
          1735927210000,
          "A202500318680"
        ]
      },
      {
        "_index": "geopoints-prod-55ad5d95-0f1d-495e-907c-5dd45a9baf09",
        "_id": "7lNmLpQByzIO-BRUDADA",
        "_score": null,
        "_source": {
          "incidentId": "A202500318866",
          "polygonCenter": [
            -82.39818451905674,
            27.911530041519057
          ],
          "customerCount": 1,
          "estimatedTimeOfRestoration": "2025-01-03T21:50:00",
          "reason": "Under investigation",
          "status": "We're working onsite",
          "updateTime": "2025-01-03T18:00:10"
        },
        "sort": [
          1735927210000,
          "A202500318866"
        ]
      }
    ]
  },
  "cache": true
}
