{
  "took": 0,
  "timed_out": false,
  "_shards": {
    "total": 1,
    "successful": 1,
    "skipped": 0,
    "failed": 0
  },
  "hits": {
    "total": {
      "value": 4,
      "relation": "eq"
    },
    "max_score": null,
    "hits": [
      {
        "_index": "geopoints-prod-598995ac-677c-450a-9a51-805820c804db",
        "_id": "7QoTupUBRYTiIU0Xvv9K",
        "_score": null,
        "_source": {
          "incidentId": "A202508037249",
          "polygonCenter": [
            -81.6753556806591,
            28.08548401831945
          ],
          "customerCount": 10,
          "estimatedTimeOfRestoration": "2025-03-21T16:50:00",
          "reason": "Pending Investigation",
          "status": "We're working onsite",
          "updateTime": "2025-03-21T15:00:05"
        },
        "sort": [
          1742569205000,
          "A202508037249"
        ]
      },
      {
        "_index": "geopoints-prod-598995ac-677c-450a-9a51-805820c804db",
        "_id": "7woTupUBRYTiIU0Xvv9K",
        "_score": null,
        "_source": {
          "incidentId": "A202508042202",
          "polygonCenter": [
            -82.2774849266795,
            28.138873033310624
          ],
          "customerCount": 10,
          "estimatedTimeOfRestoration": "2025-03-21T18:30:00",
          "reason": "Pending Investigation",
          "status": "We're on our way to investigate",
          "updateTime": "2025-03-21T15:00:05"
        },
        "sort": [
          1742569205000,
          "A202508042202"
        ]
      },
      {
        "_index": "geopoints-prod-598995ac-677c-450a-9a51-805820c804db",
        "_id": "7goTupUBRYTiIU0Xvv9K",
        "_score": null,
        "_source": {
          "incidentId": "A202508042960",
          "polygonCenter": [
            -81.73024794556898,
            28.057297151178425
          ],
          "customerCount": 7,
          "estimatedTimeOfRestoration": "2025-03-21T18:40:00",
          "reason": "Pending Investigation",
          "status": "We're working onsite",
          "updateTime": "2025-03-21T15:00:05"
        },
        "sort": [
          1742569205000,
          "A202508042960"
        ]
      },
      {
        "_index": "geopoints-prod-598995ac-677c-450a-9a51-805820c804db",
        "_id": "7AoTupUBRYTiIU0Xvv9K",
        "_score": null,
        "_source": {
          "incidentId": "A202508043263",
          "polygonCenter": [
            -82.09281000138606,
            27.955369996765036
          ],
          "customerCount": 2,
          "estimatedTimeOfRestoration": "2025-03-21T18:50:00",
          "reason": "Under investigation",
          "status": "We're working onsite",
          "updateTime": "2025-03-21T15:00:05"
        },
        "sort": [
          1742569205000,
          "A202508043263"
        ]
      }
    ]
  },
  "cache": true
}
