{
  "took": 2,
  "timed_out": false,
  "_shards": {
    "total": 1,
    "successful": 1,
    "skipped": 0,
    "failed": 0
  },
  "hits": {
    "total": {
      "value": 11,
      "relation": "eq"
    },
    "max_score": null,
    "hits": [
      {
        "_index": "geopoints-prod-4fc4fc7e-2693-4fc9-8ac4-d9b8cfa08be5",
        "_id": "o2I8vZQByzIO-BRUmc8p",
        "_score": null,
        "_source": {
          "incidentId": "A202503107399",
          "polygonCenter": [
            -82.52887737426154,
            27.894434070796386
          ],
          "customerCount": 1,
          "estimatedTimeOfRestoration": "2025-01-31T13:00:00",
          "reason": "Damage to Tampa Electric equipment",
          "status": "We're working onsite",
          "updateTime": "2025-01-31T11:40:06"
        },
        "sort": [
          1738323606000,
          "A202503107399"
        ]
      },
      {
        "_index": "geopoints-prod-4fc4fc7e-2693-4fc9-8ac4-d9b8cfa08be5",
        "_id": "q2I8vZQByzIO-BRUmc8p",
        "_score": null,
        "_source": {
          "incidentId": "A202503107939",
          "polygonCenter": [
            -82.27377537955172,
            28.021833355777012
          ],
          "customerCount": 1,
          "estimatedTimeOfRestoration": "2025-01-31T13:50:00",
          "reason": "Pending Investigation",
          "status": "We're working onsite",
          "updateTime": "2025-01-31T11:40:06"
        },
        "sort": [
          1738323606000,
          "A202503107939"
        ]
      },
      {
        "_index": "geopoints-prod-4fc4fc7e-2693-4fc9-8ac4-d9b8cfa08be5",
        "_id": "pGI8vZQByzIO-BRUmc8p",
        "_score": null,
        "_source": {
          "incidentId": "A202503108263",
          "polygonCenter": [
            -82.48970000075488,
            27.9211099967713
          ],
          "customerCount": 1,
          "estimatedTimeOfRestoration": "2025-01-31T14:00:00",
          "reason": "Damage to Tampa Electric equipment",
          "status": "We're on our way to investigate",
          "updateTime": "2025-01-31T11:40:06"
        },
        "sort": [
          1738323606000,
          "A202503108263"
        ]
      },
      {
        "_index": "geopoints-prod-4fc4fc7e-2693-4fc9-8ac4-d9b8cfa08be5",
        "_id": "rGI8vZQByzIO-BRUmc8p",
        "_score": null,
        "_source": {
          "incidentId": "A202503108453",
          "polygonCenter": [
            -82.22030499964191,
            27.90589337955693
          ],
          "customerCount": 2,
          "estimatedTimeOfRestoration": "2025-01-31T14:30:00",
          "reason": "Under investigation",
          "status": "We're working onsite",
          "updateTime": "2025-01-31T11:40:06"
        },
        "sort": [
          1738323606000,
          "A202503108453"
        ]
      },
      {
        "_index": "geopoints-prod-4fc4fc7e-2693-4fc9-8ac4-d9b8cfa08be5",
        "_id": "rWI8vZQByzIO-BRUmc8p",
        "_score": null,
        "_source": {
          "incidentId": "A202503108746",
          "polygonCenter": [
            -82.38317000081469,
            27.838279996819253
          ],
          "customerCount": 1,
          "estimatedTimeOfRestoration": "2025-01-31T15:00:00",
          "reason": "Pending Investigation",
          "status": "We're aware of the outage",
          "updateTime": "2025-01-31T11:40:06"
        },
        "sort": [
          1738323606000,
          "A202503108746"
        ]
      },
      {
        "_index": "geopoints-prod-4fc4fc7e-2693-4fc9-8ac4-d9b8cfa08be5",
        "_id": "pmI8vZQByzIO-BRUmc8p",
        "_score": null,
        "_source": {
          "incidentId": "A202503109270",
          "polygonCenter": [
            -82.41878611985429,
            28.069999867080373
          ],
          "customerCount": 209,
          "estimatedTimeOfRestoration": "2025-01-31T15:30:00",
          "reason": "Pending Investigation",
          "status": "We're aware of the outage",
          "updateTime": "2025-01-31T11:40:06"
        },
        "sort": [
          1738323606000,
          "A202503109270"
        ]
      },
      {
        "_index": "geopoints-prod-4fc4fc7e-2693-4fc9-8ac4-d9b8cfa08be5",
        "_id": "pWI8vZQByzIO-BRUmc8p",
        "_score": null,
        "_source": {
          "incidentId": "A202503109376",
          "polygonCenter": [
            -82.4891900007549,
            27.876739996796704
          ],
          "customerCount": 1,
          "estimatedTimeOfRestoration": "2025-01-31T15:40:00",
          "reason": "Pending Investigation",
          "status": "We're aware of the outage",
          "updateTime": "2025-01-31T11:40:06"
        },
        "sort": [
          1738323606000,
          "A202503109376"
        ]
      },
      {
        "_index": "geopoints-prod-4fc4fc7e-2693-4fc9-8ac4-d9b8cfa08be5",
        "_id": "p2I8vZQByzIO-BRUmc8p",
        "_score": null,
        "_source": {
          "incidentId": "A202503109382",
          "polygonCenter": [
            -81.78358000115655,
            28.078919996686395
          ],
          "customerCount": 1,
          "estimatedTimeOfRestoration": "2025-01-31T15:40:00",
          "reason": "Pending Investigation",
          "status": "We're aware of the outage",
          "updateTime": "2025-01-31T11:40:06"
        },
        "sort": [
          1738323606000,
          "A202503109382"
        ]
      },
      {
        "_index": "geopoints-prod-4fc4fc7e-2693-4fc9-8ac4-d9b8cfa08be5",
        "_id": "qGI8vZQByzIO-BRUmc8p",
        "_score": null,
        "_source": {
          "incidentId": "A202503109393",
          "polygonCenter": [
            -82.49842000074966,
            27.8824799967934
          ],
          "customerCount": 1,
          "estimatedTimeOfRestoration": "2025-01-31T15:40:00",
          "reason": "Pending Investigation",
          "status": "We're aware of the outage",
          "updateTime": "2025-01-31T11:40:06"
        },
        "sort": [
          1738323606000,
          "A202503109393"
        ]
      },
      {
        "_index": "geopoints-prod-4fc4fc7e-2693-4fc9-8ac4-d9b8cfa08be5",
        "_id": "qWI8vZQByzIO-BRUmc8p",
        "_score": null,
        "_source": {
          "incidentId": "A202503109424",
          "polygonCenter": [
            -82.48880906500248,
            27.880968059954235
          ],
          "customerCount": 6,
          "estimatedTimeOfRestoration": "2025-01-31T15:40:00",
          "reason": "Pending Investigation",
          "status": "We're aware of the outage",
          "updateTime": "2025-01-31T11:40:06"
        },
        "sort": [
          1738323606000,
          "A202503109424"
        ]
      },
      {
        "_index": "geopoints-prod-4fc4fc7e-2693-4fc9-8ac4-d9b8cfa08be5",
        "_id": "qmI8vZQByzIO-BRUmc8p",
        "_score": null,
        "_source": {
          "incidentId": "A202503109445",
          "polygonCenter": [
            -82.48602000075675,
            27.88699999679089
          ],
          "customerCount": 1,
          "estimatedTimeOfRestoration": "2025-01-31T15:40:00",
          "reason": "Pending Investigation",
          "status": "We're aware of the outage",
          "updateTime": "2025-01-31T11:40:06"
        },
        "sort": [
          1738323606000,
          "A202503109445"
        ]
      }
    ]
  },
  "cache": true
}
